gias3.visualisation-3.0.1-py3.11-nspkg.pth
gias3/visualisation/__init__.py
gias3/visualisation/fieldvi.py
gias3/visualisation/frameviewer.py
gias3/visualisation/vtkRender.py
gias3.visualisation-3.0.1.dist-info/LICENSE
gias3.visualisation-3.0.1.dist-info/METADATA
gias3.visualisation-3.0.1.dist-info/WHEEL
gias3.visualisation-3.0.1.dist-info/namespace_packages.txt
gias3.visualisation-3.0.1.dist-info/top_level.txt
gias3.visualisation-3.0.1.dist-info/RECORD
